voice_isolator/__init__.py
voice_isolator/processor.py
voice_isolator/audio/__init__.py
voice_isolator/audio/isolator.py
voice_isolator/utils/__init__.py
voice_isolator/utils/logger.py
voice_isolator/video/__init__.py
voice_isolator/video/extractor.py
voice_isolator/video/merger.py
elevenlabs_voice_isolator-0.1.0.dist-info/METADATA
elevenlabs_voice_isolator-0.1.0.dist-info/WHEEL
elevenlabs_voice_isolator-0.1.0.dist-info/entry_points.txt
elevenlabs_voice_isolator-0.1.0.dist-info/top_level.txt
elevenlabs_voice_isolator-0.1.0.dist-info/RECORD
