Metadata-Version: 2.4
Name: elevenlabs-voice-isolator
Version: 0.1.0
Summary: A package for isolating voice from video files using the ElevenLabs API
Home-page: https://github.com/tonykipkemboi/voice-isolator
Author: Tony Kipkemboi
Author-email: your.email@example.com
Project-URL: Bug Tracker, https://github.com/tonykipkemboi/voice-isolator/issues
Keywords: elevenlabs,voice isolation,audio processing,video processing,speech enhancement
Classifier: Programming Language :: Python :: 3
Classifier: Programming Language :: Python :: 3.7
Classifier: Programming Language :: Python :: 3.8
Classifier: Programming Language :: Python :: 3.9
Classifier: Programming Language :: Python :: 3.10
Classifier: License :: OSI Approved :: MIT License
Classifier: Operating System :: OS Independent
Classifier: Topic :: Multimedia :: Sound/Audio :: Speech
Classifier: Topic :: Multimedia :: Video
Requires-Python: >=3.7
Requires-Dist: elevenlabs>=1.54.0
Requires-Dist: ffmpeg-python>=0.2.0
Requires-Dist: python-dotenv>=1.0.0
Dynamic: author
Dynamic: author-email
Dynamic: classifier
Dynamic: description
Dynamic: description-content-type
Dynamic: home-page
Dynamic: keywords
Dynamic: project-url
Dynamic: requires-dist
Dynamic: requires-python
Dynamic: summary
